{
"type": "FeatureCollection",
"name": "point2",
"crs": { "type": "name", "properties": { "name": "urn:ogc:def:crs:OGC:1.3:CRS84" } },
"features": [
{ "type": "Feature", "properties": { "fid": 1, "NO.": 1, "GeN.": "T7033", "Client": "大阪市環境局", "Adress": "大阪市阿倍野区旭町１", "Lc": "市道", "Agency": "関電サービス", "status": "設置済", "lat": 34.64722346, "lng": 135.5100564, "map": 1, "Su": 1 }, "geometry": { "type": "Point", "coordinates": [ 135.5100564, 34.64722346 ] } },
{ "type": "Feature", "properties": { "fid": 2, "NO.": 2, "GeN.": "T7199", "Client": "大阪市環境局", "Adress": "大阪市阿倍野区阿倍野筋１", "Lc": "市道", "Agency": "関電サービス", "status": "設置済", "lat": 34.64668848, "lng": 135.5122308, "map": 2, "Su": 1 }, "geometry": { "type": "Point", "coordinates": [ 135.5122308, 34.64668848 ] } },
{ "type": "Feature", "properties": { "fid": 3, "NO.": 3, "GeN.": "T3263", "Client": "大阪市環境局", "Adress": "大阪市中央区南船場４", "Lc": "市道", "Agency": "関電サービス", "status": "設置済", "lat": 34.67525709, "lng": 135.4999834, "map": 3, "Su": 1 }, "geometry": { "type": "Point", "coordinates": [ 135.4999834, 34.67525709 ] } },
{ "type": "Feature", "properties": { "fid": 4, "NO.": 4, "GeN.": "T9999", "Client": "NTTdocomo", "Adress": null, "Lc": "市道", "Agency": "関電サービス", "status": "商談中", "lat": 34.7064019, "lng": 135.5109456, "map": 4, "Su": 0 }, "geometry": { "type": "Point", "coordinates": [ 135.510945600000014, 34.7064019 ] } }
]
}
